sphinx_target_theme
