Metadata-Version: 2.1
Name: sphinx-target-theme
Version: 0.0.5
Summary: Sphinx theme
Home-page: https://github.com/kkholst/sphinx_target_theme
Author: Klaus Kähler Holst
Author-email: klaus@holst.it
License: UNKNOWN
Platform: UNKNOWN
Classifier: Framework :: Sphinx
Classifier: Framework :: Sphinx :: Theme
Classifier: Programming Language :: Python :: 3
Classifier: License :: OSI Approved :: MIT License
Classifier: Operating System :: OS Independent
Classifier: Topic :: Documentation
Classifier: Topic :: Software Development :: Documentation
Requires-Python: >=3.5
